{"sequence":[33,36,45,28,51,18,44,39,54,54,47,50,38,42,22,17,21,46,53,35,46,27,31,31,50,29,25,31,31,35,37,43,33,19,47,29,37,37,37,53,27,51,46,51,50,25,24,46,36,54,15,14,47,44],"maxHeight":45,"stacks":[[{"index":53,"id":0},{"index":44,"id":20},{"index":40,"id":40},{"index":33,"id":60},{"index":45,"id":80},{"index":9,"id":100},{"index":4,"id":120},{"index":47,"id":140},{"index":53,"id":160},{"index":47,"id":180},{"index":44,"id":200},{"index":45,"id":220},{"index":32,"id":240},{"index":45,"id":260}],[{"index":41,"id":1},{"index":34,"id":21},{"index":37,"id":41},{"index":47,"id":61},{"index":14,"id":81},{"index":51,"id":101},{"index":19,"id":121},{"index":41,"id":141},{"index":54,"id":161},{"index":44,"id":181},{"index":38,"id":201},{"index":41,"id":221},{"index":39,"id":241},{"index":30,"id":261}],[{"index":15,"id":2},{"index":39,"id":22},{"index":29,"id":42},{"index":33,"id":62},{"index":36,"id":82},{"index":22,"id":102},{"index":54,"id":122},{"index":46,"id":142},{"index":26,"id":162},{"index":37,"id":182},{"index":37,"id":202},{"index":50,"id":222},{"index":38,"id":242},{"index":50,"id":262}],[{"index":50,"id":3},{"index":30,"id":23},{"index":12,"id":43},{"index":17,"id":63},{"index":41,"id":83},{"index":51,"id":103},{"index":26,"id":123},{"index":53,"id":143},{"index":43,"id":163},{"index":22,"id":183},{"index":32,"id":203},{"index":37,"id":223},{"index":24,"id":243},{"index":47,"id":263}],[{"index":18,"id":4},{"index":25,"id":24},{"index":37,"id":44},{"index":25,"id":64},{"index":33,"id":84},{"index":51,"id":104},{"index":37,"id":124},{"index":27,"id":144},{"index":42,"id":164},{"index":29,"id":184},{"index":53,"id":204},{"index":46,"id":224},{"index":13,"id":244},{"index":31,"id":264}],[{"index":18,"id":5},{"index":50,"id":25},{"index":44,"id":45},{"index":41,"id":65},{"index":49,"id":85},{"index":23,"id":105},{"index":33,"id":125},{"index":46,"id":145},{"index":15,"id":165},{"index":36,"id":185},{"index":35,"id":205},{"index":34,"id":225},{"index":29,"id":245},{"index":23,"id":265}],[{"index":19,"id":6},{"index":33,"id":26},{"index":19,"id":46},{"index":52,"id":66},{"index":36,"id":86},{"index":31,"id":106},{"index":26,"id":126},{"index":50,"id":146},{"index":51,"id":166},{"index":50,"id":186},{"index":24,"id":206},{"index":48,"id":226},{"index":33,"id":246},{"index":46,"id":266}],[{"index":50,"id":7},{"index":51,"id":27},{"index":24,"id":47},{"index":33,"id":67},{"index":47,"id":87},{"index":42,"id":107},{"index":45,"id":127},{"index":34,"id":147},{"index":26,"id":167},{"index":14,"id":187},{"index":30,"id":207},{"index":41,"id":227},{"index":37,"id":247},{"index":54,"id":267}],[{"index":29,"id":8},{"index":31,"id":28},{"index":54,"id":48},{"index":41,"id":68},{"index":47,"id":88},{"index":50,"id":108},{"index":38,"id":128},{"index":21,"id":148},{"index":30,"id":168},{"index":27,"id":188},{"index":18,"id":208},{"index":22,"id":228},{"index":28,"id":248},{"index":44,"id":268}],[{"index":34,"id":9},{"index":31,"id":29},{"index":16,"id":49},{"index":49,"id":69},{"index":38,"id":89},{"index":54,"id":109},{"index":50,"id":129},{"index":44,"id":149},{"index":53,"id":169},{"index":47,"id":189},{"index":38,"id":209},{"index":33,"id":229},{"index":41,"id":249},{"index":43,"id":269}],[{"index":19,"id":10},{"index":34,"id":30},{"index":47,"id":50},{"index":30,"id":70},{"index":47,"id":90},{"index":54,"id":110},{"index":13,"id":130},{"index":46,"id":150},{"index":38,"id":170},{"index":50,"id":190},{"index":53,"id":210},{"index":30,"id":230},{"index":43,"id":250}],[{"index":53,"id":11},{"index":4,"id":31},{"index":53,"id":51},{"index":53,"id":71},{"index":20,"id":91},{"index":48,"id":111},{"index":52,"id":131},{"index":44,"id":151},{"index":48,"id":171},{"index":43,"id":191},{"index":41,"id":211},{"index":38,"id":231},{"index":34,"id":251}],[{"index":19,"id":12},{"index":51,"id":32},{"index":47,"id":52},{"index":35,"id":72},{"index":31,"id":92},{"index":35,"id":112},{"index":52,"id":132},{"index":51,"id":152},{"index":45,"id":172},{"index":52,"id":192},{"index":17,"id":212},{"index":52,"id":232},{"index":52,"id":252}],[{"index":52,"id":13},{"index":46,"id":33},{"index":24,"id":53},{"index":51,"id":73},{"index":40,"id":93},{"index":36,"id":113},{"index":12,"id":133},{"index":17,"id":153},{"index":49,"id":173},{"index":53,"id":193},{"index":41,"id":213},{"index":24,"id":233},{"index":16,"id":253}],[{"index":20,"id":14},{"index":41,"id":34},{"index":47,"id":54},{"index":37,"id":74},{"index":32,"id":94},{"index":40,"id":114},{"index":48,"id":134},{"index":43,"id":154},{"index":50,"id":174},{"index":27,"id":194},{"index":46,"id":214},{"index":30,"id":234},{"index":34,"id":254}],[{"index":34,"id":15},{"index":32,"id":35},{"index":35,"id":55},{"index":51,"id":75},{"index":52,"id":95},{"index":44,"id":115},{"index":44,"id":135},{"index":47,"id":155},{"index":32,"id":175},{"index":29,"id":195},{"index":44,"id":215},{"index":46,"id":235},{"index":21,"id":255}],[{"index":29,"id":16},{"index":45,"id":36},{"index":49,"id":56},{"index":29,"id":76},{"index":37,"id":96},{"index":28,"id":116},{"index":33,"id":136},{"index":49,"id":156},{"index":49,"id":176},{"index":7,"id":196},{"index":46,"id":216},{"index":45,"id":236},{"index":18,"id":256}],[{"index":25,"id":17},{"index":46,"id":37},{"index":28,"id":57},{"index":45,"id":77},{"index":34,"id":97},{"index":31,"id":117},{"index":54,"id":137},{"index":34,"id":157},{"index":47,"id":177},{"index":41,"id":197},{"index":31,"id":217},{"index":27,"id":237},{"index":34,"id":257}],[{"index":27,"id":18},{"index":40,"id":38},{"index":36,"id":58},{"index":44,"id":78},{"index":36,"id":98},{"index":47,"id":118},{"index":44,"id":138},{"index":48,"id":158},{"index":49,"id":178},{"index":37,"id":198},{"index":31,"id":218},{"index":51,"id":238},{"index":40,"id":258}],[{"index":27,"id":19},{"index":50,"id":39},{"index":41,"id":59},{"index":14,"id":79},{"index":43,"id":99},{"index":33,"id":119},{"index":36,"id":139},{"index":28,"id":159},{"index":54,"id":179},{"index":39,"id":199},{"index":35,"id":219},{"index":42,"id":239},{"index":39,"id":259}]],"name":"CompanyLoadedRandom-20-45-30-54-54-linear"}