{"sequence":[67,125,112,83,66,102,73,117,110,91,106,87,35,72,47,65,29,77,95,36,121,51,100,110,113,128,91,50,56,84,129,98,103,115,117,110,80,119,102,116,79,122,18,124,123,90,124,115,97,107,127,13,23,50,51,114,81,110,83,89,76,79,81,122,67,21,73,116,119,84,129,122,79,120,116,120,73,72,116,106,101,42,67,118,70,120,123,74,84,88,111,84,113,88,128,113,22,37,95,107,71,97,48,93,61,22,120,92,73,90,44,113,61,100,103,120,97,45,61,23,93,18,106,80,105,129,82,48,58],"maxHeight":45,"stacks":[[{"index":107,"id":0},{"index":31,"id":36},{"index":110,"id":72},{"index":20,"id":108},{"index":119,"id":144},{"index":106,"id":180},{"index":126,"id":216},{"index":69,"id":252},{"index":125,"id":288},{"index":112,"id":324},{"index":107,"id":360},{"index":74,"id":396},{"index":100,"id":432},{"index":113,"id":468},{"index":89,"id":504},{"index":58,"id":540},{"index":88,"id":576},{"index":71,"id":612}],[{"index":104,"id":1},{"index":102,"id":37},{"index":101,"id":73},{"index":85,"id":109},{"index":45,"id":145},{"index":95,"id":181},{"index":106,"id":217},{"index":73,"id":253},{"index":35,"id":289},{"index":128,"id":325},{"index":128,"id":361},{"index":95,"id":397},{"index":120,"id":433},{"index":123,"id":469},{"index":75,"id":505},{"index":107,"id":541},{"index":74,"id":577},{"index":120,"id":613}],[{"index":91,"id":2},{"index":113,"id":38},{"index":60,"id":74},{"index":39,"id":110},{"index":128,"id":146},{"index":94,"id":182},{"index":86,"id":218},{"index":96,"id":254},{"index":56,"id":290},{"index":104,"id":326},{"index":47,"id":362},{"index":28,"id":398},{"index":72,"id":434},{"index":119,"id":470},{"index":60,"id":506},{"index":125,"id":542},{"index":34,"id":578},{"index":32,"id":614}],[{"index":107,"id":3},{"index":128,"id":39},{"index":123,"id":75},{"index":43,"id":111},{"index":112,"id":147},{"index":47,"id":183},{"index":31,"id":219},{"index":102,"id":255},{"index":113,"id":291},{"index":102,"id":327},{"index":62,"id":363},{"index":61,"id":399},{"index":44,"id":435},{"index":105,"id":471},{"index":52,"id":507},{"index":26,"id":543},{"index":28,"id":579},{"index":67,"id":615}],[{"index":117,"id":4},{"index":75,"id":40},{"index":7,"id":76},{"index":120,"id":112},{"index":75,"id":148},{"index":80,"id":184},{"index":73,"id":220},{"index":108,"id":256},{"index":91,"id":292},{"index":105,"id":328},{"index":108,"id":364},{"index":94,"id":400},{"index":72,"id":436},{"index":20,"id":472},{"index":119,"id":508},{"index":79,"id":544},{"index":84,"id":580},{"index":129,"id":616}],[{"index":67,"id":5},{"index":111,"id":41},{"index":73,"id":77},{"index":73,"id":113},{"index":76,"id":149},{"index":61,"id":185},{"index":66,"id":221},{"index":111,"id":257},{"index":61,"id":293},{"index":95,"id":329},{"index":47,"id":365},{"index":96,"id":401},{"index":82,"id":437},{"index":81,"id":473},{"index":82,"id":509},{"index":81,"id":545},{"index":108,"id":581},{"index":128,"id":617}],[{"index":122,"id":6},{"index":106,"id":42},{"index":103,"id":78},{"index":25,"id":114},{"index":121,"id":150},{"index":58,"id":186},{"index":108,"id":222},{"index":41,"id":258},{"index":88,"id":294},{"index":91,"id":330},{"index":105,"id":366},{"index":29,"id":402},{"index":77,"id":438},{"index":121,"id":474},{"index":118,"id":510},{"index":119,"id":546},{"index":121,"id":582},{"index":96,"id":618}],[{"index":59,"id":7},{"index":122,"id":43},{"index":52,"id":79},{"index":67,"id":115},{"index":74,"id":151},{"index":103,"id":187},{"index":95,"id":223},{"index":96,"id":259},{"index":90,"id":295},{"index":116,"id":331},{"index":66,"id":367},{"index":79,"id":403},{"index":69,"id":439},{"index":82,"id":475},{"index":86,"id":511},{"index":95,"id":547},{"index":64,"id":583},{"index":70,"id":619}],[{"index":57,"id":8},{"index":91,"id":44},{"index":22,"id":80},{"index":47,"id":116},{"index":91,"id":152},{"index":35,"id":188},{"index":96,"id":224},{"index":40,"id":260},{"index":100,"id":296},{"index":100,"id":332},{"index":124,"id":368},{"index":18,"id":404},{"index":110,"id":440},{"index":67,"id":476},{"index":85,"id":512},{"index":89,"id":548},{"index":111,"id":584},{"index":129,"id":620}],[{"index":97,"id":9},{"index":111,"id":45},{"index":114,"id":81},{"index":116,"id":117},{"index":101,"id":153},{"index":119,"id":189},{"index":44,"id":225},{"index":94,"id":261},{"index":68,"id":297},{"index":89,"id":333},{"index":62,"id":369},{"index":69,"id":405},{"index":97,"id":441},{"index":49,"id":477},{"index":97,"id":513},{"index":54,"id":549},{"index":80,"id":585},{"index":100,"id":621}],[{"index":110,"id":10},{"index":70,"id":46},{"index":58,"id":82},{"index":52,"id":118},{"index":101,"id":154},{"index":100,"id":190},{"index":27,"id":226},{"index":110,"id":262},{"index":7,"id":298},{"index":114,"id":334},{"index":124,"id":370},{"index":20,"id":406},{"index":123,"id":442},{"index":63,"id":478},{"index":62,"id":514},{"index":42,"id":550},{"index":53,"id":586},{"index":95,"id":622}],[{"index":46,"id":11},{"index":93,"id":47},{"index":95,"id":83},{"index":126,"id":119},{"index":81,"id":155},{"index":104,"id":191},{"index":40,"id":227},{"index":13,"id":263},{"index":93,"id":299},{"index":91,"id":335},{"index":91,"id":371},{"index":102,"id":407},{"index":104,"id":443},{"index":76,"id":479},{"index":109,"id":515},{"index":122,"id":551},{"index":58,"id":587},{"index":29,"id":623}],[{"index":78,"id":12},{"index":120,"id":48},{"index":92,"id":84},{"index":126,"id":120},{"index":88,"id":156},{"index":118,"id":192},{"index":100,"id":228},{"index":115,"id":264},{"index":78,"id":300},{"index":100,"id":336},{"index":25,"id":372},{"index":106,"id":408},{"index":121,"id":444},{"index":109,"id":480},{"index":82,"id":516},{"index":37,"id":552},{"index":88,"id":588},{"index":128,"id":624}],[{"index":123,"id":13},{"index":36,"id":49},{"index":127,"id":85},{"index":48,"id":121},{"index":81,"id":157},{"index":128,"id":193},{"index":91,"id":229},{"index":107,"id":265},{"index":124,"id":301},{"index":107,"id":337},{"index":59,"id":373},{"index":84,"id":409},{"index":67,"id":445},{"index":87,"id":481},{"index":84,"id":517},{"index":129,"id":553},{"index":64,"id":589},{"index":70,"id":625}],[{"index":122,"id":14},{"index":97,"id":50},{"index":48,"id":86},{"index":92,"id":122},{"index":47,"id":158},{"index":103,"id":194},{"index":116,"id":230},{"index":63,"id":266},{"index":102,"id":302},{"index":87,"id":338},{"index":20,"id":374},{"index":79,"id":410},{"index":114,"id":446},{"index":108,"id":482},{"index":100,"id":518},{"index":103,"id":554},{"index":24,"id":590},{"index":16,"id":626}],[{"index":46,"id":15},{"index":124,"id":51},{"index":98,"id":87},{"index":82,"id":123},{"index":67,"id":159},{"index":108,"id":195},{"index":39,"id":231},{"index":116,"id":267},{"index":78,"id":303},{"index":59,"id":339},{"index":117,"id":375},{"index":126,"id":411},{"index":93,"id":447},{"index":106,"id":483},{"index":36,"id":519},{"index":24,"id":555},{"index":129,"id":591},{"index":84,"id":627}],[{"index":98,"id":16},{"index":123,"id":52},{"index":111,"id":88},{"index":67,"id":124},{"index":103,"id":160},{"index":23,"id":196},{"index":82,"id":232},{"index":114,"id":268},{"index":49,"id":304},{"index":98,"id":340},{"index":85,"id":376},{"index":41,"id":412},{"index":54,"id":448},{"index":82,"id":484},{"index":90,"id":520},{"index":38,"id":556},{"index":82,"id":592},{"index":121,"id":628}],[{"index":126,"id":17},{"index":64,"id":53},{"index":105,"id":89},{"index":29,"id":125},{"index":92,"id":161},{"index":32,"id":197},{"index":125,"id":233},{"index":86,"id":269},{"index":128,"id":305},{"index":102,"id":341},{"index":118,"id":377},{"index":25,"id":413},{"index":82,"id":449},{"index":84,"id":485},{"index":112,"id":521},{"index":129,"id":557},{"index":118,"id":593},{"index":117,"id":629}],[{"index":124,"id":18},{"index":86,"id":54},{"index":119,"id":90},{"index":121,"id":126},{"index":43,"id":162},{"index":43,"id":198},{"index":118,"id":234},{"index":71,"id":270},{"index":107,"id":306},{"index":112,"id":342},{"index":73,"id":378},{"index":53,"id":414},{"index":69,"id":450},{"index":104,"id":486},{"index":127,"id":522},{"index":51,"id":558},{"index":111,"id":594},{"index":110,"id":630}],[{"index":120,"id":19},{"index":53,"id":55},{"index":11,"id":91},{"index":97,"id":127},{"index":111,"id":163},{"index":122,"id":199},{"index":108,"id":235},{"index":68,"id":271},{"index":122,"id":307},{"index":113,"id":343},{"index":112,"id":379},{"index":81,"id":415},{"index":69,"id":451},{"index":82,"id":487},{"index":123,"id":523},{"index":44,"id":559},{"index":115,"id":595},{"index":112,"id":631}],[{"index":34,"id":20},{"index":110,"id":56},{"index":123,"id":92},{"index":113,"id":128},{"index":106,"id":164},{"index":121,"id":200},{"index":106,"id":236},{"index":117,"id":272},{"index":22,"id":308},{"index":76,"id":344},{"index":124,"id":380},{"index":85,"id":416},{"index":119,"id":452},{"index":106,"id":488},{"index":126,"id":524},{"index":103,"id":560},{"index":93,"id":596},{"index":69,"id":632}],[{"index":107,"id":21},{"index":121,"id":57},{"index":50,"id":93},{"index":92,"id":129},{"index":100,"id":165},{"index":13,"id":201},{"index":110,"id":237},{"index":96,"id":273},{"index":119,"id":309},{"index":128,"id":345},{"index":99,"id":381},{"index":80,"id":417},{"index":128,"id":453},{"index":127,"id":489},{"index":88,"id":525},{"index":110,"id":561},{"index":44,"id":597},{"index":77,"id":633}],[{"index":115,"id":22},{"index":109,"id":58},{"index":109,"id":94},{"index":104,"id":130},{"index":48,"id":166},{"index":69,"id":202},{"index":71,"id":238},{"index":88,"id":274},{"index":112,"id":310},{"index":97,"id":346},{"index":102,"id":382},{"index":107,"id":418},{"index":123,"id":454},{"index":116,"id":490},{"index":110,"id":526},{"index":122,"id":562},{"index":94,"id":598},{"index":35,"id":634}],[{"index":105,"id":23},{"index":119,"id":59},{"index":123,"id":95},{"index":106,"id":131},{"index":73,"id":167},{"index":103,"id":203},{"index":128,"id":239},{"index":82,"id":275},{"index":83,"id":311},{"index":103,"id":347},{"index":77,"id":383},{"index":122,"id":419},{"index":83,"id":455},{"index":76,"id":491},{"index":56,"id":527},{"index":84,"id":563},{"index":128,"id":599},{"index":47,"id":635}],[{"index":92,"id":24},{"index":88,"id":60},{"index":127,"id":96},{"index":91,"id":132},{"index":104,"id":168},{"index":118,"id":204},{"index":104,"id":240},{"index":73,"id":276},{"index":36,"id":312},{"index":106,"id":348},{"index":112,"id":384},{"index":92,"id":420},{"index":49,"id":456},{"index":124,"id":492},{"index":82,"id":528},{"index":113,"id":564},{"index":98,"id":600},{"index":108,"id":636}],[{"index":120,"id":25},{"index":102,"id":61},{"index":122,"id":97},{"index":85,"id":133},{"index":35,"id":169},{"index":95,"id":205},{"index":93,"id":241},{"index":78,"id":277},{"index":104,"id":313},{"index":58,"id":349},{"index":68,"id":385},{"index":120,"id":421},{"index":95,"id":457},{"index":21,"id":493},{"index":32,"id":529},{"index":118,"id":565},{"index":121,"id":601},{"index":65,"id":637}],[{"index":82,"id":26},{"index":113,"id":62},{"index":18,"id":98},{"index":117,"id":134},{"index":23,"id":170},{"index":67,"id":206},{"index":124,"id":242},{"index":22,"id":278},{"index":94,"id":314},{"index":94,"id":350},{"index":102,"id":386},{"index":87,"id":422},{"index":61,"id":458},{"index":113,"id":494},{"index":118,"id":530},{"index":13,"id":566},{"index":93,"id":602},{"index":84,"id":638}],[{"index":42,"id":27},{"index":110,"id":63},{"index":52,"id":99},{"index":104,"id":135},{"index":103,"id":171},{"index":40,"id":207},{"index":48,"id":243},{"index":70,"id":279},{"index":79,"id":315},{"index":53,"id":351},{"index":63,"id":387},{"index":18,"id":423},{"index":56,"id":459},{"index":88,"id":495},{"index":95,"id":531},{"index":100,"id":567},{"index":116,"id":603},{"index":106,"id":639}],[{"index":24,"id":28},{"index":91,"id":64},{"index":120,"id":100},{"index":42,"id":136},{"index":63,"id":172},{"index":117,"id":208},{"index":90,"id":244},{"index":88,"id":280},{"index":21,"id":316},{"index":76,"id":352},{"index":34,"id":388},{"index":118,"id":424},{"index":93,"id":460},{"index":50,"id":496},{"index":48,"id":532},{"index":84,"id":568},{"index":54,"id":604},{"index":93,"id":640}],[{"index":112,"id":29},{"index":79,"id":65},{"index":87,"id":101},{"index":53,"id":137},{"index":83,"id":173},{"index":76,"id":209},{"index":79,"id":245},{"index":114,"id":281},{"index":113,"id":317},{"index":73,"id":353},{"index":67,"id":389},{"index":73,"id":425},{"index":52,"id":461},{"index":122,"id":497},{"index":116,"id":533},{"index":71,"id":569},{"index":9,"id":605},{"index":92,"id":641}],[{"index":95,"id":30},{"index":87,"id":66},{"index":45,"id":102},{"index":110,"id":138},{"index":27,"id":174},{"index":56,"id":210},{"index":82,"id":246},{"index":91,"id":282},{"index":72,"id":318},{"index":89,"id":354},{"index":45,"id":390},{"index":114,"id":426},{"index":68,"id":462},{"index":57,"id":498},{"index":119,"id":534},{"index":114,"id":570},{"index":44,"id":606},{"index":66,"id":642}],[{"index":83,"id":31},{"index":99,"id":67},{"index":91,"id":103},{"index":108,"id":139},{"index":35,"id":175},{"index":82,"id":211},{"index":76,"id":247},{"index":48,"id":283},{"index":111,"id":319},{"index":110,"id":355},{"index":51,"id":391},{"index":113,"id":427},{"index":64,"id":463},{"index":68,"id":499},{"index":105,"id":535},{"index":102,"id":571},{"index":91,"id":607},{"index":48,"id":643}],[{"index":118,"id":32},{"index":98,"id":68},{"index":113,"id":104},{"index":81,"id":140},{"index":75,"id":176},{"index":98,"id":212},{"index":96,"id":248},{"index":80,"id":284},{"index":116,"id":320},{"index":120,"id":356},{"index":29,"id":392},{"index":44,"id":428},{"index":87,"id":464},{"index":88,"id":500},{"index":74,"id":536},{"index":104,"id":572},{"index":21,"id":608},{"index":103,"id":644}],[{"index":87,"id":33},{"index":46,"id":69},{"index":41,"id":105},{"index":85,"id":141},{"index":100,"id":177},{"index":104,"id":213},{"index":56,"id":249},{"index":99,"id":285},{"index":116,"id":321},{"index":94,"id":357},{"index":115,"id":393},{"index":32,"id":429},{"index":116,"id":465},{"index":44,"id":501},{"index":74,"id":537},{"index":112,"id":573},{"index":111,"id":609},{"index":111,"id":645}],[{"index":108,"id":34},{"index":119,"id":70},{"index":114,"id":106},{"index":122,"id":142},{"index":83,"id":178},{"index":66,"id":214},{"index":128,"id":250},{"index":98,"id":286},{"index":51,"id":322},{"index":34,"id":358},{"index":119,"id":394},{"index":68,"id":430},{"index":112,"id":466},{"index":121,"id":502},{"index":93,"id":538},{"index":122,"id":574},{"index":44,"id":610},{"index":115,"id":646}],[{"index":110,"id":35},{"index":125,"id":71},{"index":84,"id":107},{"index":61,"id":143},{"index":125,"id":179},{"index":125,"id":215},{"index":37,"id":251},{"index":40,"id":287},{"index":117,"id":323},{"index":107,"id":359},{"index":61,"id":395},{"index":112,"id":431},{"index":29,"id":467},{"index":70,"id":503},{"index":113,"id":539},{"index":39,"id":575},{"index":89,"id":611},{"index":126,"id":647}]],"name":"CompanyLoadedRandom-36-45-40-129-129-linear"}