{"sequence":[26,43,31,24,3,36,23,34,8,27,26,19,43,19,36,42,40,31,32,11,6,21,30,28,17,32,36,18,20,30,24,26,41,39,10,16,33,19,41,25,39,22,14],"maxHeight":45,"stacks":[[{"index":39,"id":0},{"index":25,"id":12},{"index":40,"id":24},{"index":26,"id":36},{"index":26,"id":48},{"index":22,"id":60},{"index":9,"id":72},{"index":11,"id":84},{"index":28,"id":96},{"index":43,"id":108},{"index":38,"id":120},{"index":35,"id":132},{"index":26,"id":144},{"index":36,"id":156},{"index":27,"id":168},{"index":40,"id":180},{"index":22,"id":192},{"index":39,"id":204}],[{"index":25,"id":1},{"index":32,"id":13},{"index":26,"id":25},{"index":37,"id":37},{"index":41,"id":49},{"index":20,"id":61},{"index":42,"id":73},{"index":14,"id":85},{"index":16,"id":97},{"index":37,"id":109},{"index":34,"id":121},{"index":17,"id":133},{"index":14,"id":145},{"index":26,"id":157},{"index":28,"id":169},{"index":8,"id":181},{"index":32,"id":193},{"index":14,"id":205}],[{"index":3,"id":2},{"index":42,"id":14},{"index":30,"id":26},{"index":14,"id":38},{"index":17,"id":50},{"index":31,"id":62},{"index":31,"id":74},{"index":25,"id":86},{"index":36,"id":98},{"index":30,"id":110},{"index":43,"id":122},{"index":42,"id":134},{"index":41,"id":146},{"index":23,"id":158},{"index":24,"id":170},{"index":42,"id":182},{"index":33,"id":194},{"index":26,"id":206}],[{"index":30,"id":3},{"index":19,"id":15},{"index":37,"id":27},{"index":37,"id":39},{"index":17,"id":51},{"index":41,"id":63},{"index":25,"id":75},{"index":40,"id":87},{"index":11,"id":99},{"index":42,"id":111},{"index":31,"id":123},{"index":31,"id":135},{"index":27,"id":147},{"index":40,"id":159},{"index":24,"id":171},{"index":43,"id":183},{"index":40,"id":195},{"index":26,"id":207}],[{"index":10,"id":4},{"index":36,"id":16},{"index":42,"id":28},{"index":21,"id":40},{"index":17,"id":52},{"index":42,"id":64},{"index":17,"id":76},{"index":43,"id":88},{"index":41,"id":100},{"index":38,"id":112},{"index":32,"id":124},{"index":27,"id":136},{"index":19,"id":148},{"index":41,"id":160},{"index":35,"id":172},{"index":32,"id":184},{"index":8,"id":196},{"index":34,"id":208}],[{"index":37,"id":5},{"index":42,"id":17},{"index":37,"id":29},{"index":43,"id":41},{"index":26,"id":53},{"index":41,"id":65},{"index":43,"id":77},{"index":34,"id":89},{"index":21,"id":101},{"index":28,"id":113},{"index":4,"id":125},{"index":33,"id":137},{"index":32,"id":149},{"index":42,"id":161},{"index":20,"id":173},{"index":22,"id":185},{"index":36,"id":197},{"index":31,"id":209}],[{"index":41,"id":6},{"index":32,"id":18},{"index":20,"id":30},{"index":38,"id":42},{"index":28,"id":54},{"index":11,"id":66},{"index":33,"id":78},{"index":31,"id":90},{"index":19,"id":102},{"index":39,"id":114},{"index":4,"id":126},{"index":28,"id":138},{"index":42,"id":150},{"index":40,"id":162},{"index":30,"id":174},{"index":32,"id":186},{"index":13,"id":198},{"index":14,"id":210}],[{"index":42,"id":7},{"index":36,"id":19},{"index":19,"id":31},{"index":31,"id":43},{"index":20,"id":55},{"index":23,"id":67},{"index":30,"id":79},{"index":41,"id":91},{"index":18,"id":103},{"index":27,"id":115},{"index":41,"id":127},{"index":32,"id":139},{"index":26,"id":151},{"index":26,"id":163},{"index":21,"id":175},{"index":39,"id":187},{"index":32,"id":199},{"index":24,"id":211}],[{"index":42,"id":8},{"index":30,"id":20},{"index":27,"id":32},{"index":23,"id":44},{"index":28,"id":56},{"index":42,"id":68},{"index":19,"id":80},{"index":34,"id":92},{"index":22,"id":104},{"index":28,"id":116},{"index":25,"id":128},{"index":12,"id":140},{"index":43,"id":152},{"index":36,"id":164},{"index":35,"id":176},{"index":26,"id":188},{"index":36,"id":200},{"index":3,"id":212}],[{"index":42,"id":9},{"index":39,"id":21},{"index":16,"id":33},{"index":20,"id":45},{"index":15,"id":57},{"index":42,"id":69},{"index":18,"id":81},{"index":41,"id":93},{"index":31,"id":105},{"index":43,"id":117},{"index":42,"id":129},{"index":16,"id":141},{"index":41,"id":153},{"index":24,"id":165},{"index":25,"id":177},{"index":19,"id":189},{"index":14,"id":201},{"index":17,"id":213}],[{"index":33,"id":10},{"index":34,"id":22},{"index":32,"id":34},{"index":39,"id":46},{"index":29,"id":58},{"index":6,"id":70},{"index":19,"id":82},{"index":28,"id":94},{"index":34,"id":106},{"index":40,"id":118},{"index":19,"id":130},{"index":41,"id":142},{"index":33,"id":154},{"index":34,"id":166},{"index":27,"id":178},{"index":33,"id":190},{"index":33,"id":202},{"index":37,"id":214}],[{"index":26,"id":11},{"index":24,"id":23},{"index":20,"id":35},{"index":37,"id":47},{"index":30,"id":59},{"index":38,"id":71},{"index":43,"id":83},{"index":18,"id":95},{"index":33,"id":107},{"index":12,"id":119},{"index":33,"id":131},{"index":12,"id":143},{"index":36,"id":155},{"index":30,"id":167},{"index":36,"id":179},{"index":43,"id":191},{"index":21,"id":203},{"index":32,"id":215}]],"name":"CompanyLoadedRandom-12-45-40-43-43-linear"}