{"sequence":[106,111,77,100,23,64,33,99,74,39,102,93,50,117,58,118,69,44,98,87,104,60,99,88,82,49,114,118,61,59,82,108,109,97,115,116,100,107,78,83,69,97,53,71,96,57,60,75,63,31,73,89,114,22,84,39,108,43,32,18,99,112,111,111,87,104,82,111,35,101,30,65,43,114,67,57,67,116,83,60,99,112,116,110,115,108,91,61,62,85,33,107,118,117,106,90,59,117,84,94,12,116,99,100,92,105,106,104,28,96,79,16,115,104,25,111,48,53],"maxHeight":45,"stacks":[[{"index":113,"id":0},{"index":94,"id":33},{"index":59,"id":66},{"index":104,"id":99},{"index":80,"id":132},{"index":100,"id":165},{"index":37,"id":198},{"index":68,"id":231},{"index":89,"id":264},{"index":96,"id":297},{"index":91,"id":330},{"index":84,"id":363},{"index":111,"id":396},{"index":63,"id":429},{"index":84,"id":462},{"index":79,"id":495},{"index":111,"id":528},{"index":110,"id":561}],[{"index":84,"id":1},{"index":101,"id":34},{"index":34,"id":67},{"index":90,"id":100},{"index":84,"id":133},{"index":102,"id":166},{"index":99,"id":199},{"index":92,"id":232},{"index":109,"id":265},{"index":101,"id":298},{"index":50,"id":331},{"index":28,"id":364},{"index":71,"id":397},{"index":102,"id":430},{"index":116,"id":463},{"index":101,"id":496},{"index":53,"id":529},{"index":61,"id":562}],[{"index":10,"id":2},{"index":75,"id":35},{"index":22,"id":68},{"index":68,"id":101},{"index":113,"id":134},{"index":43,"id":167},{"index":26,"id":200},{"index":62,"id":233},{"index":39,"id":266},{"index":102,"id":299},{"index":99,"id":332},{"index":12,"id":365},{"index":50,"id":398},{"index":82,"id":431},{"index":41,"id":464},{"index":107,"id":497},{"index":57,"id":530},{"index":82,"id":563}],[{"index":39,"id":3},{"index":56,"id":36},{"index":44,"id":69},{"index":111,"id":102},{"index":86,"id":135},{"index":98,"id":168},{"index":117,"id":201},{"index":107,"id":234},{"index":115,"id":267},{"index":103,"id":300},{"index":79,"id":333},{"index":42,"id":366},{"index":99,"id":399},{"index":109,"id":432},{"index":116,"id":465},{"index":70,"id":498},{"index":57,"id":531},{"index":101,"id":564}],[{"index":117,"id":4},{"index":118,"id":37},{"index":117,"id":70},{"index":114,"id":103},{"index":104,"id":136},{"index":73,"id":169},{"index":91,"id":202},{"index":118,"id":235},{"index":115,"id":268},{"index":114,"id":301},{"index":114,"id":334},{"index":92,"id":367},{"index":21,"id":400},{"index":27,"id":433},{"index":110,"id":466},{"index":72,"id":499},{"index":114,"id":532},{"index":44,"id":565}],[{"index":74,"id":5},{"index":33,"id":38},{"index":45,"id":71},{"index":69,"id":104},{"index":118,"id":137},{"index":85,"id":170},{"index":45,"id":203},{"index":91,"id":236},{"index":117,"id":269},{"index":114,"id":302},{"index":110,"id":335},{"index":100,"id":368},{"index":73,"id":401},{"index":88,"id":434},{"index":105,"id":467},{"index":101,"id":500},{"index":50,"id":533},{"index":109,"id":566}],[{"index":76,"id":6},{"index":94,"id":39},{"index":90,"id":72},{"index":89,"id":105},{"index":31,"id":138},{"index":87,"id":171},{"index":116,"id":204},{"index":108,"id":237},{"index":94,"id":270},{"index":109,"id":303},{"index":110,"id":336},{"index":24,"id":369},{"index":27,"id":402},{"index":59,"id":435},{"index":102,"id":468},{"index":47,"id":501},{"index":67,"id":534},{"index":35,"id":567}],[{"index":97,"id":7},{"index":95,"id":40},{"index":50,"id":73},{"index":62,"id":106},{"index":74,"id":139},{"index":91,"id":172},{"index":54,"id":205},{"index":43,"id":238},{"index":90,"id":271},{"index":82,"id":304},{"index":52,"id":337},{"index":90,"id":370},{"index":77,"id":403},{"index":107,"id":436},{"index":117,"id":469},{"index":94,"id":502},{"index":107,"id":535},{"index":82,"id":568}],[{"index":94,"id":8},{"index":111,"id":41},{"index":52,"id":74},{"index":65,"id":107},{"index":28,"id":140},{"index":59,"id":173},{"index":109,"id":206},{"index":37,"id":239},{"index":20,"id":272},{"index":76,"id":305},{"index":105,"id":338},{"index":57,"id":371},{"index":59,"id":404},{"index":99,"id":437},{"index":117,"id":470},{"index":58,"id":503},{"index":81,"id":536},{"index":83,"id":569}],[{"index":71,"id":9},{"index":94,"id":42},{"index":112,"id":75},{"index":114,"id":108},{"index":103,"id":141},{"index":78,"id":174},{"index":37,"id":207},{"index":47,"id":240},{"index":79,"id":273},{"index":10,"id":306},{"index":72,"id":339},{"index":33,"id":372},{"index":91,"id":405},{"index":88,"id":438},{"index":69,"id":471},{"index":83,"id":504},{"index":32,"id":537},{"index":116,"id":570}],[{"index":43,"id":10},{"index":97,"id":43},{"index":116,"id":76},{"index":99,"id":109},{"index":113,"id":142},{"index":100,"id":175},{"index":88,"id":208},{"index":44,"id":241},{"index":87,"id":274},{"index":45,"id":307},{"index":105,"id":340},{"index":96,"id":373},{"index":58,"id":406},{"index":82,"id":439},{"index":111,"id":472},{"index":73,"id":505},{"index":67,"id":538},{"index":104,"id":571}],[{"index":43,"id":11},{"index":85,"id":44},{"index":110,"id":77},{"index":54,"id":110},{"index":94,"id":143},{"index":47,"id":176},{"index":94,"id":209},{"index":74,"id":242},{"index":82,"id":275},{"index":50,"id":308},{"index":59,"id":341},{"index":81,"id":374},{"index":84,"id":407},{"index":116,"id":440},{"index":101,"id":473},{"index":108,"id":506},{"index":106,"id":539},{"index":60,"id":572}],[{"index":65,"id":12},{"index":112,"id":45},{"index":104,"id":78},{"index":72,"id":111},{"index":88,"id":144},{"index":106,"id":177},{"index":45,"id":210},{"index":60,"id":243},{"index":85,"id":276},{"index":117,"id":309},{"index":67,"id":342},{"index":114,"id":375},{"index":114,"id":408},{"index":13,"id":441},{"index":84,"id":474},{"index":82,"id":507},{"index":87,"id":540},{"index":38,"id":573}],[{"index":85,"id":13},{"index":85,"id":46},{"index":115,"id":79},{"index":98,"id":112},{"index":115,"id":145},{"index":41,"id":178},{"index":110,"id":211},{"index":112,"id":244},{"index":110,"id":277},{"index":113,"id":310},{"index":85,"id":343},{"index":112,"id":376},{"index":64,"id":409},{"index":106,"id":442},{"index":72,"id":475},{"index":93,"id":508},{"index":116,"id":541},{"index":78,"id":574}],[{"index":21,"id":14},{"index":96,"id":47},{"index":99,"id":80},{"index":103,"id":113},{"index":106,"id":146},{"index":117,"id":179},{"index":112,"id":212},{"index":108,"id":245},{"index":30,"id":278},{"index":25,"id":311},{"index":68,"id":344},{"index":97,"id":377},{"index":90,"id":410},{"index":85,"id":443},{"index":117,"id":476},{"index":43,"id":509},{"index":52,"id":542},{"index":111,"id":575}],[{"index":50,"id":15},{"index":57,"id":48},{"index":83,"id":81},{"index":79,"id":114},{"index":94,"id":147},{"index":85,"id":180},{"index":57,"id":213},{"index":33,"id":246},{"index":67,"id":279},{"index":92,"id":312},{"index":81,"id":345},{"index":31,"id":378},{"index":87,"id":411},{"index":69,"id":444},{"index":74,"id":477},{"index":58,"id":510},{"index":50,"id":543},{"index":92,"id":576}],[{"index":99,"id":16},{"index":76,"id":49},{"index":26,"id":82},{"index":88,"id":115},{"index":53,"id":148},{"index":111,"id":181},{"index":115,"id":214},{"index":79,"id":247},{"index":113,"id":280},{"index":90,"id":313},{"index":69,"id":346},{"index":104,"id":379},{"index":44,"id":412},{"index":45,"id":445},{"index":118,"id":478},{"index":54,"id":511},{"index":71,"id":544},{"index":41,"id":577}],[{"index":84,"id":17},{"index":79,"id":50},{"index":96,"id":83},{"index":70,"id":116},{"index":51,"id":149},{"index":100,"id":182},{"index":69,"id":215},{"index":64,"id":248},{"index":37,"id":281},{"index":104,"id":314},{"index":106,"id":347},{"index":80,"id":380},{"index":83,"id":413},{"index":107,"id":446},{"index":111,"id":479},{"index":90,"id":512},{"index":42,"id":545},{"index":75,"id":578}],[{"index":101,"id":18},{"index":110,"id":51},{"index":112,"id":84},{"index":85,"id":117},{"index":21,"id":150},{"index":87,"id":183},{"index":30,"id":216},{"index":55,"id":249},{"index":14,"id":282},{"index":58,"id":315},{"index":30,"id":348},{"index":93,"id":381},{"index":48,"id":414},{"index":82,"id":447},{"index":57,"id":480},{"index":71,"id":513},{"index":62,"id":546},{"index":103,"id":579}],[{"index":55,"id":19},{"index":55,"id":52},{"index":112,"id":85},{"index":45,"id":118},{"index":48,"id":151},{"index":76,"id":184},{"index":68,"id":217},{"index":117,"id":250},{"index":94,"id":283},{"index":100,"id":316},{"index":72,"id":349},{"index":108,"id":382},{"index":85,"id":415},{"index":62,"id":448},{"index":59,"id":481},{"index":22,"id":514},{"index":77,"id":547},{"index":112,"id":580}],[{"index":56,"id":20},{"index":117,"id":53},{"index":113,"id":86},{"index":60,"id":119},{"index":54,"id":152},{"index":80,"id":185},{"index":59,"id":218},{"index":105,"id":251},{"index":103,"id":284},{"index":32,"id":317},{"index":88,"id":350},{"index":23,"id":383},{"index":116,"id":416},{"index":98,"id":449},{"index":16,"id":482},{"index":60,"id":515},{"index":97,"id":548},{"index":110,"id":581}],[{"index":30,"id":21},{"index":61,"id":54},{"index":61,"id":87},{"index":52,"id":120},{"index":108,"id":153},{"index":94,"id":186},{"index":50,"id":219},{"index":116,"id":252},{"index":100,"id":285},{"index":105,"id":318},{"index":21,"id":351},{"index":76,"id":384},{"index":88,"id":417},{"index":52,"id":450},{"index":64,"id":483},{"index":94,"id":516},{"index":87,"id":549},{"index":108,"id":582}],[{"index":101,"id":22},{"index":107,"id":55},{"index":60,"id":88},{"index":109,"id":121},{"index":21,"id":154},{"index":105,"id":187},{"index":90,"id":220},{"index":56,"id":253},{"index":104,"id":286},{"index":46,"id":319},{"index":72,"id":352},{"index":87,"id":385},{"index":78,"id":418},{"index":80,"id":451},{"index":69,"id":484},{"index":111,"id":517},{"index":115,"id":550},{"index":42,"id":583}],[{"index":104,"id":23},{"index":37,"id":56},{"index":34,"id":89},{"index":86,"id":122},{"index":12,"id":155},{"index":97,"id":188},{"index":38,"id":221},{"index":111,"id":254},{"index":97,"id":287},{"index":63,"id":320},{"index":57,"id":353},{"index":34,"id":386},{"index":91,"id":419},{"index":113,"id":452},{"index":101,"id":485},{"index":114,"id":518},{"index":104,"id":551},{"index":27,"id":584}],[{"index":33,"id":24},{"index":105,"id":57},{"index":99,"id":90},{"index":115,"id":123},{"index":101,"id":156},{"index":60,"id":189},{"index":45,"id":222},{"index":100,"id":255},{"index":89,"id":288},{"index":76,"id":321},{"index":99,"id":354},{"index":89,"id":387},{"index":21,"id":420},{"index":24,"id":453},{"index":58,"id":486},{"index":86,"id":519},{"index":82,"id":552},{"index":88,"id":585}],[{"index":82,"id":25},{"index":61,"id":58},{"index":109,"id":91},{"index":76,"id":124},{"index":43,"id":157},{"index":35,"id":190},{"index":97,"id":223},{"index":49,"id":256},{"index":96,"id":289},{"index":41,"id":322},{"index":101,"id":355},{"index":46,"id":388},{"index":116,"id":421},{"index":111,"id":454},{"index":50,"id":487},{"index":112,"id":520},{"index":66,"id":553},{"index":117,"id":586}],[{"index":111,"id":26},{"index":114,"id":59},{"index":100,"id":92},{"index":15,"id":125},{"index":103,"id":158},{"index":116,"id":191},{"index":74,"id":224},{"index":39,"id":257},{"index":99,"id":290},{"index":91,"id":323},{"index":32,"id":356},{"index":31,"id":389},{"index":113,"id":422},{"index":25,"id":455},{"index":3,"id":488},{"index":80,"id":521},{"index":105,"id":554},{"index":28,"id":587}],[{"index":60,"id":27},{"index":61,"id":60},{"index":98,"id":93},{"index":29,"id":126},{"index":117,"id":159},{"index":111,"id":192},{"index":93,"id":225},{"index":112,"id":258},{"index":101,"id":291},{"index":98,"id":324},{"index":114,"id":357},{"index":59,"id":390},{"index":108,"id":423},{"index":78,"id":456},{"index":67,"id":489},{"index":88,"id":522},{"index":115,"id":555},{"index":56,"id":588}],[{"index":110,"id":28},{"index":58,"id":61},{"index":69,"id":94},{"index":59,"id":127},{"index":115,"id":160},{"index":117,"id":193},{"index":116,"id":226},{"index":118,"id":259},{"index":118,"id":292},{"index":111,"id":325},{"index":93,"id":358},{"index":107,"id":391},{"index":77,"id":424},{"index":32,"id":457},{"index":111,"id":490},{"index":73,"id":523},{"index":103,"id":556},{"index":114,"id":589}],[{"index":48,"id":29},{"index":42,"id":62},{"index":117,"id":95},{"index":45,"id":128},{"index":88,"id":161},{"index":39,"id":194},{"index":116,"id":227},{"index":71,"id":260},{"index":39,"id":293},{"index":106,"id":326},{"index":47,"id":359},{"index":110,"id":392},{"index":55,"id":425},{"index":63,"id":458},{"index":67,"id":491},{"index":52,"id":524},{"index":96,"id":557},{"index":109,"id":590}],[{"index":63,"id":30},{"index":98,"id":63},{"index":8,"id":96},{"index":37,"id":129},{"index":95,"id":162},{"index":85,"id":195},{"index":18,"id":228},{"index":111,"id":261},{"index":49,"id":294},{"index":96,"id":327},{"index":82,"id":360},{"index":69,"id":393},{"index":114,"id":426},{"index":109,"id":459},{"index":51,"id":492},{"index":115,"id":525},{"index":35,"id":558},{"index":113,"id":591}],[{"index":54,"id":31},{"index":44,"id":64},{"index":104,"id":97},{"index":92,"id":130},{"index":112,"id":163},{"index":112,"id":196},{"index":35,"id":229},{"index":77,"id":262},{"index":90,"id":295},{"index":71,"id":328},{"index":40,"id":361},{"index":90,"id":394},{"index":19,"id":427},{"index":96,"id":460},{"index":82,"id":493},{"index":108,"id":526},{"index":88,"id":559},{"index":100,"id":592}],[{"index":83,"id":32},{"index":86,"id":65},{"index":81,"id":98},{"index":104,"id":131},{"index":87,"id":164},{"index":37,"id":197},{"index":87,"id":230},{"index":107,"id":263},{"index":95,"id":296},{"index":91,"id":329},{"index":109,"id":362},{"index":20,"id":395},{"index":54,"id":428},{"index":91,"id":461},{"index":87,"id":494},{"index":9,"id":527},{"index":93,"id":560},{"index":69,"id":593}]],"name":"CompanyLoadedRandom-33-45-40-118-118-linear"}