{"sequence":[83,60,87,79,75,63,83,57,75,68,17,58,29,40,52,85,90,48,72,80,94,70,83,23,92,62,81,34,81,77,43,39,82,35,46,58,84,59,61,83,81,81,52,73,82,65,60,62,88,68,74,37,78,95,61,96,39,54,90,91,24,80,43,67,94,69,31,71,34,84,40,84,82,94,73,72,62,22,64,61,78,40,77,78,30,32,89,11,94,69,8,55,65,28,60,15],"maxHeight":60,"stacks":[[{"index":61,"id":0},{"index":74,"id":20},{"index":63,"id":40},{"index":93,"id":60},{"index":82,"id":80},{"index":62,"id":100},{"index":56,"id":120},{"index":58,"id":140},{"index":54,"id":160},{"index":82,"id":180},{"index":72,"id":200},{"index":81,"id":220},{"index":96,"id":240},{"index":30,"id":260},{"index":83,"id":280},{"index":84,"id":300},{"index":43,"id":320},{"index":85,"id":340},{"index":68,"id":360},{"index":44,"id":380},{"index":78,"id":400},{"index":76,"id":420},{"index":52,"id":440},{"index":81,"id":460}],[{"index":76,"id":1},{"index":67,"id":21},{"index":84,"id":41},{"index":32,"id":61},{"index":95,"id":81},{"index":48,"id":101},{"index":68,"id":121},{"index":90,"id":141},{"index":94,"id":161},{"index":58,"id":181},{"index":87,"id":201},{"index":73,"id":221},{"index":74,"id":241},{"index":34,"id":261},{"index":48,"id":281},{"index":89,"id":301},{"index":90,"id":321},{"index":47,"id":341},{"index":72,"id":361},{"index":58,"id":381},{"index":42,"id":401},{"index":79,"id":421},{"index":65,"id":441},{"index":69,"id":461}],[{"index":46,"id":2},{"index":52,"id":22},{"index":92,"id":42},{"index":77,"id":62},{"index":94,"id":82},{"index":82,"id":102},{"index":55,"id":122},{"index":61,"id":142},{"index":40,"id":162},{"index":66,"id":182},{"index":85,"id":202},{"index":54,"id":222},{"index":78,"id":242},{"index":93,"id":262},{"index":71,"id":282},{"index":48,"id":302},{"index":70,"id":322},{"index":9,"id":342},{"index":66,"id":362},{"index":78,"id":382},{"index":52,"id":402},{"index":86,"id":422},{"index":25,"id":442},{"index":59,"id":462}],[{"index":59,"id":3},{"index":57,"id":23},{"index":68,"id":43},{"index":94,"id":63},{"index":87,"id":83},{"index":76,"id":103},{"index":69,"id":123},{"index":58,"id":143},{"index":22,"id":163},{"index":75,"id":183},{"index":73,"id":203},{"index":95,"id":223},{"index":73,"id":243},{"index":41,"id":263},{"index":84,"id":283},{"index":49,"id":303},{"index":94,"id":323},{"index":93,"id":343},{"index":55,"id":363},{"index":90,"id":383},{"index":62,"id":403},{"index":90,"id":423},{"index":70,"id":443},{"index":54,"id":463}],[{"index":81,"id":4},{"index":93,"id":24},{"index":83,"id":44},{"index":82,"id":64},{"index":84,"id":84},{"index":76,"id":104},{"index":56,"id":124},{"index":84,"id":144},{"index":49,"id":164},{"index":46,"id":184},{"index":47,"id":204},{"index":80,"id":224},{"index":79,"id":244},{"index":89,"id":264},{"index":64,"id":284},{"index":90,"id":304},{"index":91,"id":324},{"index":90,"id":344},{"index":43,"id":364},{"index":40,"id":384},{"index":94,"id":404},{"index":95,"id":424},{"index":82,"id":444},{"index":52,"id":464}],[{"index":58,"id":5},{"index":60,"id":25},{"index":43,"id":45},{"index":62,"id":65},{"index":90,"id":85},{"index":39,"id":105},{"index":87,"id":125},{"index":43,"id":145},{"index":67,"id":165},{"index":9,"id":185},{"index":45,"id":205},{"index":79,"id":225},{"index":52,"id":245},{"index":95,"id":265},{"index":48,"id":285},{"index":45,"id":305},{"index":49,"id":325},{"index":73,"id":345},{"index":42,"id":365},{"index":71,"id":385},{"index":59,"id":405},{"index":45,"id":425},{"index":71,"id":445},{"index":35,"id":465}],[{"index":95,"id":6},{"index":38,"id":26},{"index":83,"id":46},{"index":89,"id":66},{"index":41,"id":86},{"index":83,"id":106},{"index":64,"id":126},{"index":77,"id":146},{"index":62,"id":166},{"index":79,"id":186},{"index":39,"id":206},{"index":87,"id":226},{"index":93,"id":246},{"index":96,"id":266},{"index":60,"id":286},{"index":29,"id":306},{"index":69,"id":326},{"index":96,"id":346},{"index":61,"id":366},{"index":65,"id":386},{"index":88,"id":406},{"index":47,"id":426},{"index":65,"id":446},{"index":24,"id":466}],[{"index":78,"id":7},{"index":55,"id":27},{"index":72,"id":47},{"index":87,"id":67},{"index":81,"id":87},{"index":60,"id":107},{"index":96,"id":127},{"index":24,"id":147},{"index":89,"id":167},{"index":96,"id":187},{"index":58,"id":207},{"index":82,"id":227},{"index":80,"id":247},{"index":66,"id":267},{"index":78,"id":287},{"index":94,"id":307},{"index":68,"id":327},{"index":69,"id":347},{"index":56,"id":367},{"index":69,"id":387},{"index":83,"id":407},{"index":28,"id":427},{"index":57,"id":447},{"index":90,"id":467}],[{"index":41,"id":8},{"index":91,"id":28},{"index":49,"id":48},{"index":91,"id":68},{"index":91,"id":88},{"index":39,"id":108},{"index":60,"id":128},{"index":32,"id":148},{"index":52,"id":168},{"index":95,"id":188},{"index":88,"id":208},{"index":40,"id":228},{"index":79,"id":248},{"index":78,"id":268},{"index":91,"id":288},{"index":81,"id":308},{"index":74,"id":328},{"index":34,"id":348},{"index":69,"id":368},{"index":14,"id":388},{"index":72,"id":408},{"index":67,"id":428},{"index":94,"id":448},{"index":81,"id":468}],[{"index":30,"id":9},{"index":55,"id":29},{"index":60,"id":49},{"index":93,"id":69},{"index":78,"id":89},{"index":93,"id":109},{"index":87,"id":129},{"index":95,"id":149},{"index":82,"id":169},{"index":62,"id":189},{"index":54,"id":209},{"index":83,"id":229},{"index":19,"id":249},{"index":81,"id":269},{"index":84,"id":289},{"index":52,"id":309},{"index":16,"id":329},{"index":78,"id":349},{"index":65,"id":369},{"index":86,"id":389},{"index":62,"id":409},{"index":64,"id":429},{"index":73,"id":449},{"index":65,"id":469}],[{"index":23,"id":10},{"index":82,"id":30},{"index":57,"id":50},{"index":57,"id":70},{"index":64,"id":90},{"index":12,"id":110},{"index":94,"id":130},{"index":85,"id":150},{"index":59,"id":170},{"index":56,"id":190},{"index":26,"id":210},{"index":41,"id":230},{"index":38,"id":250},{"index":58,"id":270},{"index":71,"id":290},{"index":70,"id":310},{"index":56,"id":330},{"index":59,"id":350},{"index":41,"id":370},{"index":56,"id":390},{"index":59,"id":410},{"index":61,"id":430},{"index":90,"id":450},{"index":57,"id":470}],[{"index":36,"id":11},{"index":22,"id":31},{"index":35,"id":51},{"index":21,"id":71},{"index":17,"id":91},{"index":52,"id":111},{"index":94,"id":131},{"index":65,"id":151},{"index":75,"id":171},{"index":15,"id":191},{"index":73,"id":211},{"index":39,"id":231},{"index":76,"id":251},{"index":75,"id":271},{"index":94,"id":291},{"index":95,"id":311},{"index":80,"id":331},{"index":59,"id":351},{"index":47,"id":371},{"index":57,"id":391},{"index":83,"id":411},{"index":83,"id":431},{"index":48,"id":451},{"index":81,"id":471}],[{"index":92,"id":12},{"index":61,"id":32},{"index":58,"id":52},{"index":24,"id":72},{"index":61,"id":92},{"index":14,"id":112},{"index":68,"id":132},{"index":15,"id":152},{"index":62,"id":172},{"index":84,"id":192},{"index":64,"id":212},{"index":53,"id":232},{"index":46,"id":252},{"index":73,"id":272},{"index":81,"id":292},{"index":66,"id":312},{"index":44,"id":332},{"index":78,"id":352},{"index":74,"id":372},{"index":63,"id":392},{"index":21,"id":412},{"index":91,"id":432},{"index":21,"id":452},{"index":74,"id":472}],[{"index":45,"id":13},{"index":55,"id":33},{"index":53,"id":53},{"index":14,"id":73},{"index":94,"id":93},{"index":28,"id":113},{"index":61,"id":133},{"index":94,"id":153},{"index":83,"id":173},{"index":95,"id":193},{"index":79,"id":213},{"index":32,"id":233},{"index":35,"id":253},{"index":69,"id":273},{"index":73,"id":293},{"index":84,"id":313},{"index":81,"id":333},{"index":66,"id":353},{"index":75,"id":373},{"index":86,"id":393},{"index":69,"id":413},{"index":85,"id":433},{"index":96,"id":453},{"index":72,"id":473}],[{"index":51,"id":14},{"index":69,"id":34},{"index":29,"id":54},{"index":61,"id":74},{"index":79,"id":94},{"index":80,"id":114},{"index":76,"id":134},{"index":79,"id":154},{"index":44,"id":174},{"index":78,"id":194},{"index":36,"id":214},{"index":77,"id":234},{"index":36,"id":254},{"index":38,"id":274},{"index":80,"id":294},{"index":94,"id":314},{"index":48,"id":334},{"index":82,"id":354},{"index":85,"id":374},{"index":41,"id":394},{"index":62,"id":414},{"index":84,"id":434},{"index":59,"id":454},{"index":54,"id":474}],[{"index":69,"id":15},{"index":81,"id":35},{"index":45,"id":55},{"index":56,"id":75},{"index":72,"id":95},{"index":26,"id":115},{"index":43,"id":135},{"index":80,"id":155},{"index":91,"id":175},{"index":62,"id":195},{"index":94,"id":215},{"index":84,"id":235},{"index":67,"id":255},{"index":83,"id":275},{"index":32,"id":295},{"index":51,"id":315},{"index":88,"id":335},{"index":91,"id":355},{"index":64,"id":375},{"index":76,"id":395},{"index":66,"id":415},{"index":89,"id":435},{"index":72,"id":455},{"index":86,"id":475}],[{"index":34,"id":16},{"index":8,"id":36},{"index":58,"id":56},{"index":41,"id":76},{"index":75,"id":96},{"index":92,"id":116},{"index":46,"id":136},{"index":77,"id":156},{"index":36,"id":176},{"index":77,"id":196},{"index":82,"id":216},{"index":83,"id":236},{"index":51,"id":256},{"index":55,"id":276},{"index":56,"id":296},{"index":73,"id":316},{"index":53,"id":336},{"index":18,"id":356},{"index":52,"id":376},{"index":90,"id":396},{"index":96,"id":416},{"index":67,"id":436},{"index":96,"id":456},{"index":48,"id":476}],[{"index":79,"id":17},{"index":78,"id":37},{"index":54,"id":57},{"index":90,"id":77},{"index":68,"id":97},{"index":71,"id":117},{"index":37,"id":137},{"index":40,"id":157},{"index":20,"id":177},{"index":74,"id":197},{"index":63,"id":217},{"index":91,"id":237},{"index":40,"id":257},{"index":89,"id":277},{"index":69,"id":297},{"index":34,"id":317},{"index":20,"id":337},{"index":79,"id":357},{"index":49,"id":377},{"index":42,"id":397},{"index":95,"id":417},{"index":83,"id":437},{"index":60,"id":457},{"index":80,"id":477}],[{"index":65,"id":18},{"index":22,"id":38},{"index":9,"id":58},{"index":79,"id":78},{"index":47,"id":98},{"index":32,"id":118},{"index":75,"id":138},{"index":54,"id":158},{"index":82,"id":178},{"index":28,"id":198},{"index":84,"id":218},{"index":95,"id":238},{"index":91,"id":258},{"index":96,"id":278},{"index":57,"id":298},{"index":44,"id":318},{"index":46,"id":338},{"index":41,"id":358},{"index":58,"id":378},{"index":31,"id":398},{"index":91,"id":418},{"index":87,"id":438},{"index":45,"id":458},{"index":33,"id":478}],[{"index":61,"id":19},{"index":57,"id":39},{"index":29,"id":59},{"index":87,"id":79},{"index":77,"id":99},{"index":64,"id":119},{"index":92,"id":139},{"index":82,"id":159},{"index":75,"id":179},{"index":70,"id":199},{"index":90,"id":219},{"index":63,"id":239},{"index":41,"id":259},{"index":34,"id":279},{"index":43,"id":299},{"index":62,"id":319},{"index":44,"id":339},{"index":33,"id":359},{"index":11,"id":379},{"index":32,"id":399},{"index":31,"id":419},{"index":39,"id":439},{"index":54,"id":459},{"index":60,"id":479}]],"name":"CompanyLoadedRandom-20-60-40-96-96-linear"}